openapydantic/__init__.py
openapydantic/common.py
openapydantic/py.typed
openapydantic/resolver.py
openapydantic/versions/__init__.py
openapydantic/versions/openapi_302/__init__.py
openapydantic/versions/openapi_302/models.py
openapydantic-0.2.3.dist-info/LICENSE
openapydantic-0.2.3.dist-info/WHEEL
openapydantic-0.2.3.dist-info/METADATA
openapydantic-0.2.3.dist-info/RECORD
