Metadata-Version: 2.1
Name: openapydantic
Version: 0.2.3
Summary: openapi specification parser based on pydantic
Home-page: https://github.com/richarddevers/openapydantic
License: MIT
Keywords: openapi,swagger,pydantic,api,rest
Author: Richard Devers
Author-email: ritchiedev25@gmail.com
Requires-Python: >=3.8,<4.0
Classifier: License :: OSI Approved :: MIT License
Classifier: Programming Language :: Python :: 3
Classifier: Programming Language :: Python :: 3.10
Classifier: Programming Language :: Python :: 3.8
Classifier: Programming Language :: Python :: 3.9
Requires-Dist: email-validator (>=1.1.3,<2.0.0)
Requires-Dist: jsonpath-ng (>=1.5.3,<2.0.0)
Requires-Dist: pydantic (>=1.9.0,<2.0.0)
Requires-Dist: pyyaml (>=5.3.1)
Requires-Dist: types-PyYAML (>=6.0.5,<7.0.0)
Project-URL: Repository, https://github.com/richarddevers/openapydantic
